img2scan2pdf/__init__.py
img2scan2pdf/cli.py
img2scan2pdf/utils.py
img2scan2pdf-0.1.0.dist-info/LICENSE
img2scan2pdf-0.1.0.dist-info/METADATA
img2scan2pdf-0.1.0.dist-info/WHEEL
img2scan2pdf-0.1.0.dist-info/entry_points.txt
img2scan2pdf-0.1.0.dist-info/top_level.txt
img2scan2pdf-0.1.0.dist-info/RECORD
