Metadata-Version: 2.2
Name: img2scan2pdf
Version: 0.1.0
Summary: A CLI tool to process images and convert them to a PDF.
Home-page: https://github.com/PalamarchukOleksii/img2scan2pdf
Author: Oleksii Palamarchuk
Author-email: oleksiypalamarchuck@gmail.com
Classifier: Programming Language :: Python :: 3
Classifier: License :: OSI Approved :: MIT License
Classifier: Operating System :: OS Independent
Requires-Python: >=3.7
License-File: LICENSE
Requires-Dist: numpy
Requires-Dist: opencv-python
Requires-Dist: Pillow
Dynamic: author
Dynamic: author-email
Dynamic: classifier
Dynamic: description
Dynamic: description-content-type
Dynamic: home-page
Dynamic: requires-dist
Dynamic: requires-python
Dynamic: summary
